{
  "news_id": "k10011343931000",
  "news_prearranged_time": "2018-02-28 11:30:00",
  "title": "本よりスマホで読む漫画の売り上げのほうが多くなる",
  "title_with_ruby": "<ruby>本<rt>ほん</rt></ruby>よりスマホで<ruby>読<rt>よ</rt></ruby>む<ruby>漫画<rt>まんが</rt></ruby>の<ruby>売<rt>う</rt></ruby>り<ruby>上<rt>あ</rt></ruby>げのほうが<ruby>多<rt>おお</rt></ruby>くなる",
  "outline_with_ruby": "<p><ruby>出版科学研究所<rt>しゅっぱんかがくけんきゅうじょ</rt></ruby>によると、<ruby>去年<rt>きょねん</rt></ruby><a href='javascript:void(0)' class='dicWin' id='id-0001'><ruby>売<rt>う</rt></ruby>れ</a>た<ruby>漫画<rt>まんが</rt></ruby>は<ruby>全部<rt>ぜんぶ</rt></ruby>で３３７７<ruby>億<rt>おく</rt></ruby><ruby>円<rt>えん</rt></ruby>で、おととしより０．９％<ruby>少<rt>すく</rt></ruby>なくなりました。",
  "has_news_web_image": false,
  "has_news_web_movie": false,
  "has_news_easy_image": true,
  "has_news_easy_movie": false,
  "has_news_easy_voice": true,
  "news_web_image_uri": "",
  "news_web_movie_uri": "",
  "news_easy_image_uri": "k10011343931000.jpg",
  "news_easy_movie_uri": "''",
  "news_easy_voice_uri": "k10011343931000.mp3",
  "url": "http://www3.nhk.or.jp/news/easy/k10011343931000/k10011343931000.html"
}