{
  "cate": "1",
  "date": "2æ26æ¥ 17æ39å",
  "datetime": "2018-02-26T17:39",
  "video": "",
  "duration": 0,
  "img": "html/20180226/K10011343841_1802261730_1802261737_01_02.jpg",
  "title": "米Ｆ16タンク投棄で大量のシジミを廃棄 「宝物を捨て無念」",
  "summary": "アメリカ軍三沢基地の戦闘機が青森県東北町の小川原湖に燃料タンクを投棄した問題で、２６日、地元の漁協は投棄のあとに水揚げされた特産のシジミ４００キロ近くを、「安全性が確保できない」として廃棄しました。一方、三沢基地トップの司令官が東北町役場を訪れ、町長に初めて謝罪しました。",
  "more": "",
  "body": [
    {
      "title": "",
      "img": "html/20180226/K10011343841_1802261730_1802261737_01_03.jpg",
      "align": "right",
      "text": "今月２０日、三沢基地に所属するＦ１６戦闘機が離陸直後にエンジン火災を起こし、燃料タンク２つを小川原湖に投棄して基地に引き返しました。この影響で、湖では水質悪化が懸念されて漁が全面的に禁止になり、自衛隊が、湖の底からタンクの残骸などを回収する作業にあたっています。<br /><br />こうした中、地元の小川原湖漁業協同組合は、タンクが投棄された今月２０日に水揚げされた特産のシジミ３８５キロを「安全性が確保できない」として、すべて廃棄しました。<br />漁協の担当者たちは、湖岸の荷さばき施設で保管していたシジミを、トラックに載せて地元のゴミ処理施設に運び入れていました。<br /><br />小川原湖漁業協同組合の濱田正隆組合長は「われわれにとって宝物のシジミを捨てることは非常に無念だ」と話していました。<br /><br />小川原湖はシジミ、シラウオ、それにワカサギの全国有数の産地で、シジミの漁獲量は年間１０００トン余りに上り、漁協は禁漁に伴う補償を青森県を通じて国に求めています。",
      "textPos": ""
    },
    {
      "title": "米司令官が初めて謝罪",
      "img": "html/20180226/K10011343841_1802261737_1802261738_01_04.jpg",
      "align": "right",
      "text": "一方、三沢基地のＲ・スコット・ジョーブ司令官が、２６日午前９時ごろ、東北町役場を訪れ、蛯名鉱治町長と面会しました。<br /><br />関係者によりますと、司令官と町長はおよそ３０分話し合い、司令官が謝罪するとともに、町長はタンクの残骸などの早期回収の実現にアメリカ軍としても努めるよう求めたということです。<br /><br />話し合いのあと、ジョーブ司令官は「地域の住民、漁業者、町に、大きな影響を与えてしまったことについて謝罪しました。湖の原状回復に向けて、引き続き協力していきたい」と話していました。<br /><br />ジョーブ司令官はタンクを投棄した今月２０日、基地のある三沢市の市役所を訪れ謝っていますが、漁業者に影響が出ている東北町に謝罪するのは初めてです。蛯名町長は「もっと早く直接謝罪をしてほしかった」と話していました。<br /><br />また、小川原湖漁業協同組合によりますと、ジョーブ司令官は２６日午前９時前、漁協の事務所を訪れ、濱田正隆組合長に対しても初めて直接、謝罪したということです。",
      "textPos": ""
    }
  ],
  "relationNews": [
    {
      "link": "html/20180224/k10011341991000.html",
      "title": "米軍機 燃料タンク投棄 海上自衛隊が残骸を回収",
      "date": "2月24日  21時23分",
      "datetime": "2018-02-24T21:23",
      "imgPath": "html/20180224/K10011341991_1802242119_1802242123_01_02.jpg",
      "iconPath": "html/20180224/K10011341991_1802242119_1802242123_02_01.jpg",
      "video": "",
      "duration": 0
    },
    {
      "link": "html/20180222/k10011338731000.html",
      "title": "米軍機の燃料タンク投棄 燃料除去へ調査始める 自衛隊",
      "date": "2月22日  19時04分",
      "datetime": "2018-02-22T19:04",
      "imgPath": "html/20180222/K10011338731_1802221214_1802221220_01_03.jpg",
      "iconPath": "html/20180222/K10011338731_1802221214_1802221220_02_01.jpg",
      "video": "https://www3.nhk.or.jp/news/html/20180222/movie/k10011338731_201802221214_201802221214.html",
      "duration": 60
    },
    {
      "link": "html/20180221/k10011336811000.html",
      "title": "米軍機燃料タンク投棄 地元漁協 漁禁止で補償請求へ",
      "date": "2月21日  5時04分",
      "datetime": "2018-02-21T05:04",
      "imgPath": "html/20180221/K10011336811_1802210552_1802210555_01_03.jpg",
      "iconPath": "html/20180221/K10011336811_1802210552_1802210555_02_01.jpg",
      "video": "https://www3.nhk.or.jp/news/html/20180221/movie/k10011336811_201802210552_201802210555.html",
      "duration": 47
    }
  ],
  "relationLink": [
    {
      "link": "https://www9.nhk.or.jp/nw9/digest/2018/02/0220.html",
      "title": "米軍戦闘機から あわや…",
      "time": "ニュースウオッチ９ 2月20日",
      "datetime": "2018-02-20"
    }
  ],
  "word": [],
  "news_id": "k10011343841000",
  "yyyy": "2018",
  "mm": "02",
  "dd": "26",
  "url": "https://www3.nhk.or.jp/news/html/20180226/k10011343841000.html"
}