{
  "cate": "2",
  "date": "2æ7æ¥ 19æ57å",
  "datetime": "2018-02-07T19:57",
  "video": "/news/html/20180207/movie/k10011319561_201802072040_201802072041.html",
  "duration": 87,
  "img": "html/20180207/K10011319561_1802072041_1802072041_01_03.jpg",
  "title": "日本庭園ランクで足立美術館が１５年連続日本一 島根",
  "summary": "島根県安来市の足立美術館の庭園が、アメリカの専門誌による日本庭園のランキングで、１５年連続で日本一に選ばれました。",
  "more": "島根県安来市の足立美術館には、およそ１６．５ヘクタールの敷地に、石と白い砂で山や水の流れを表現した枯山水庭など６つの日本庭園が設けられています。<br /><br />アメリカで出版されている日本庭園の専門誌「ジャーナル・オブ・ジャパニーズ・ガーデニング」は、毎年日本国内の庭園を審査して、独自のランキングを発表しています。去年は庭園の専門家３０人が、全国にある９００か所以上の日本庭園を調査し、庭園の質や建物との調和利用者への対応などを審査した結果、足立美術館の庭園が１５年連続で日本一に選ばれました。<br /><br />２位は京都市の桂離宮、３位は東京 柴又の山本亭と去年と同じ順位でした。<br /><br />専門誌は「日本庭園の愛好家であれば、“スーパースター”である足立美術館を鑑賞するために、島根を訪れなければならない」と評価しています。<br /><br />足立美術館の足立隆則館長は「日本を代表する庭園に選ばれた誇りを胸に、館員一丸となってその魅力を世界に発信していきたい」とコメントしています。",
  "body": [
    {
      "title": "",
      "img": "",
      "align": "",
      "text": "",
      "textPos": ""
    }
  ],
  "relationNews": [],
  "relationLink": [
    {
      "link": "http://www3.nhk.or.jp/news/easy/k10011319561000/k10011319561000.html",
      "title": "島根県の足立美術館が日本の庭園のランキングで１番になる",
      "time": "NEWSWEB EASY 2月9日",
      "datetime": "2018-02-09"
    }
  ],
  "word": [],
  "news_id": "k10011319561000",
  "yyyy": "2018",
  "mm": "02",
  "dd": "07",
  "url": "https://www3.nhk.or.jp/news/html/20180207/k10011319561000.html"
}